prediction_module/__init__.py
prediction_module/io/Load_db.py
prediction_module/io/__init__.py
prediction_module/preprocess/__init__.py
prediction_module/preprocess/df_as_u_want.py
prediction_module_poncheele-0.0.1.dist-info/METADATA
prediction_module_poncheele-0.0.1.dist-info/RECORD
prediction_module_poncheele-0.0.1.dist-info/WHEEL
prediction_module_poncheele-0.0.1.dist-info/top_level.txt
