Metadata-Version: 2.1
Name: prediction-module-poncheele
Version: 0.0.1
Summary: make a prediction for fds mtp
Home-page: https://github.com/Poncheele/Prediction_velo
Author: Poncheele
Author-email: clementponcheele@gmail.com
License: FDS
Platform: UNKNOWN
